yyszh/__init__.py
yyszh/hit_stopwords.py
yyszh/utils.py
yyszh/word_cloud_diagram.py
yyszh-0.1.8.dist-info/METADATA
yyszh-0.1.8.dist-info/WHEEL
yyszh-0.1.8.dist-info/top_level.txt
yyszh-0.1.8.dist-info/RECORD
